aioliqpay/__init__.py
aioliqpay/liqpay3.py
aioliqpay-1.0.0.dist-info/METADATA
aioliqpay-1.0.0.dist-info/WHEEL
aioliqpay-1.0.0.dist-info/top_level.txt
aioliqpay-1.0.0.dist-info/RECORD
