Metadata-Version: 2.1
Name: aioliqpay
Version: 1.0.0
Summary: Asyncio LiqPay SDK for Python
Author-email: toxazhl <zhltoxa@gmail.com>
Project-URL: Homepage, https://github.com/toxazhl/aioliqpay
Keywords: aioliqpay,liqpay,asyncio,sdk
Classifier: License :: OSI Approved :: MIT License
Classifier: Programming Language :: Python :: 3.6
Classifier: Programming Language :: Python :: 3.7
Classifier: Programming Language :: Python :: 3.8
Classifier: Programming Language :: Python :: 3.9
Classifier: Programming Language :: Python :: 3.10
Requires-Python: >=3.6
Requires-Dist: aiohttp
Provides-Extra: dev
Requires-Dist: black ; extra == 'dev'
Requires-Dist: bumpver ; extra == 'dev'
Requires-Dist: isort ; extra == 'dev'
Requires-Dist: pip-tools ; extra == 'dev'
Requires-Dist: pytest ; extra == 'dev'
